denonremote/__about__.py
denonremote/__init__.py
denonremote/__main__.py
denonremote/cli.py
denonremote/denonremote.kv
denonremote/gui.py
denonremote/denon/__init__.py
denonremote/denon/communication.py
denonremote/denon/dn500av.py
denonremote/fonts/FreeSerif.ttf
denonremote/fonts/RobotoMono-Bold.ttf
denonremote/fonts/RobotoMono-BoldItalic.ttf
denonremote/fonts/RobotoMono-Italic.ttf
denonremote/fonts/RobotoMono-Regular.ttf
denonremote/fonts/Unicode_IEC_symbol.ttf
denonremote/images/DN-500AV.png
denonremote/images/icon.png
denonremote/settings/communication.json
denonremote/settings/source1.json
denonremote/settings/source2.json
denonremote/settings/source3.json
denonremote/settings/source4.json
denonremote/settings/source5.json
denonremote/settings/source6.json
denonremote/settings/volume.json
denonremote/settings/volume_display.json
denonremote/settings/window.json
src/denonremote/__build__.py
denonremote-0.10.0.dist-info/METADATA
denonremote-0.10.0.dist-info/WHEEL
denonremote-0.10.0.dist-info/entry_points.txt
denonremote-0.10.0.dist-info/licenses/LICENSE
denonremote-0.10.0.dist-info/RECORD
