Metadata-Version: 2.1
Name: denonremote
Version: 0.10.0
Summary: A desktop GUI remote for the Denon DN-500 AV receiver.
Project-URL: Homepage, https://github.com/ematech/denonremote
Project-URL: Issues, https://github.com/ematech/denonremote/issues
Author-email: Raphaël Doursenaud <rdoursenaud@free.fr>
License: GNU GENERAL PUBLIC LICENSE
License-File: LICENSE
Keywords: DN-500AV,Denon,Remote control
Classifier: Development Status :: 4 - Beta
Classifier: Environment :: MacOS X
Classifier: Environment :: Win32 (MS Windows)
Classifier: Environment :: X11 Applications
Classifier: Framework :: Twisted
Classifier: Intended Audience :: End Users/Desktop
Classifier: License :: OSI Approved :: GNU General Public License v3 or later (GPLv3+)
Classifier: Natural Language :: English
Classifier: Operating System :: MacOS :: MacOS X
Classifier: Operating System :: Microsoft :: Windows :: Windows 10
Classifier: Operating System :: Microsoft :: Windows :: Windows 11
Classifier: Operating System :: POSIX :: Linux
Classifier: Programming Language :: Python :: 3
Classifier: Programming Language :: Python :: 3 :: Only
Classifier: Programming Language :: Python :: 3.10
Classifier: Programming Language :: Python :: 3.11
Classifier: Topic :: Home Automation
Classifier: Topic :: Multimedia :: Sound/Audio
Classifier: Topic :: Scientific/Engineering :: Human Machine Interfaces
Classifier: Topic :: Utilities
Classifier: Typing :: Typed
Requires-Python: ~=3.10
Requires-Dist: kivy[sdl2]==2.2.1
Requires-Dist: kivyontop==1.4
Requires-Dist: pillow~=9.5.0
Requires-Dist: pystray==0.19.4
Requires-Dist: twisted==22.10.0
